Metadata-Version: 2.1
Name: mavefund
Version: 0.0.7
Summary: The official API client for the MaveFund.com
Home-page: https://github.com/ddjerqq/mavefund
Author: ddjerqq
Author-email: ddjerqq@gmail.com
License: GNU
Keywords: mavefund stocks investing datascience finance
Platform: UNKNOWN
License-File: LICENSE
